README
setup.py
firebrowse/LICENSE.txt
firebrowse/VERSION
firebrowse/__init__.py
firebrowse/cli.py
firebrowse/fbcore.py
firebrowse/fbimap.py
firebrowse/fbmap.py
firebrowse/generate.py
firebrowse/highlevel.py
firebrowse/lowlevel.py
firebrowse/parse.py
firebrowse/template.setup
firebrowse.egg-info/PKG-INFO
firebrowse.egg-info/SOURCES.txt
firebrowse.egg-info/dependency_links.txt
firebrowse.egg-info/entry_points.txt
firebrowse.egg-info/requires.txt
firebrowse.egg-info/top_level.txt