Metadata-Version: 1.0
Name: firebrowse
Version: 0.1.10
Summary: firebrowse portal API bindings for Python
Home-page: http://firebrowse.org/api/api-docs
Author: Michael S. Noble, via fbgen code generator
Author-email: gdac@broadinstitute.org
License: Broad Institute, MIT/BSD-style
Platform: UNKNOWN
